[
  {
    "([47, 26, 99],)": "NO result"
  },
  {
    "([100, 18, 56],)": "NO result"
  },
  {
    "([39, 86, 80],)": "NO result"
  },
  {
    "([95, 54, 34],)": "NO result"
  },
  {
    "([57, 62, 15],)": [
      -0.36323455893005263,
      -0.7244847393155615
    ]
  },
  {
    "([60, 60, 13],)": [
      -0.3174258141649446,
      -0.6825741858350554
    ]
  },
  {
    "([55, 30, 7],)": "NO result"
  },
  {
    "([93, 3, 92],)": "NO result"
  },
  {
    "([5, 97, 91],)": [
      -0.9885133300911264,
      -18.411486669908875
    ]
  },
  {
    "([47, 98, 19],)": [
      -0.21631966642776174,
      -1.8687867165509617
    ]
  },
  {
    "([20, 79, 65],)": [
      -1.168386709754916,
      -2.781613290245084
    ]
  },
  {
    "([23, 64, 18],)": [
      -0.31747051867578535,
      -2.4651381769763883
    ]
  },
  {
    "([95, 42, 48],)": "NO result"
  },
  {
    "([94, 23, 2],)": "NO result"
  },
  {
    "([67, 71, 5],)": [
      -0.07585190524611553,
      -0.9838495872911979
    ]
  },
  {
    "([31, 53, 78],)": "NO result"
  },
  {
    "([35, 47, 60],)": "NO result"
  },
  {
    "([43, 33, 9],)": "NO result"
  },
  {
    "([43, 94, 34],)": [
      -0.45741161075737446,
      -1.7286349008705324
    ]
  },
  {
    "([33, 41, 34],)": "NO result"
  },
  {
    "([63, 98, 8],)": [
      -0.08643550030531535,
      -1.4691200552502401
    ]
  },
  {
    "([16, 83, 12],)": [
      -0.14884937574141865,
      -5.038650624258581
    ]
  },
  {
    "([1, 69, 27],)": [
      -0.39354899729378445,
      -68.60645100270622
    ]
  },
  {
    "([99, 14, 66],)": "NO result"
  },
  {
    "([7, 3, 66],)": "NO result"
  },
  {
    "([54, 6, 95],)": "NO result"
  },
  {
    "([5, 71, 100],)": [
      -1.585473728415105,
      -12.614526271584896
    ]
  },
  {
    "([6, 5, 49],)": "NO result"
  },
  {
    "([8, 53, 81],)": [
      -2.3918175085839852,
      -4.233182491416015
    ]
  },
  {
    "([84, 27, 87],)": "NO result"
  },
  {
    "([82, 50, 48],)": "NO result"
  },
  {
    "([19, 74, 28],)": [
      -0.4246867219484808,
      -3.4700501201567824
    ]
  },
  {
    "([87, 23, 49],)": "NO result"
  },
  {
    "([91, 46, 18],)": "NO result"
  },
  {
    "([53, 73, 53],)": "NO result"
  },
  {
    "([33, 94, 69],)": "NO result"
  },
  {
    "([23, 99, 67],)": [
      -0.8411403231900346,
      -3.4632075028969216
    ]
  },
  {
    "([79, 75, 87],)": "NO result"
  },
  {
    "([3, 35, 66],)": [
      -2.3652246588858645,
      -9.301442007780802
    ]
  },
  {
    "([54, 54, 11],)": [
      -0.2848342585440324,
      -0.7151657414559677
    ]
  },
  {
    "([44, 25, 48],)": "NO result"
  },
  {
    "([62, 3, 13],)": "NO result"
  },
  {
    "([15, 92, 24],)": [
      -0.2730230880324048,
      -5.860310245300928
    ]
  },
  {
    "([94, 36, 98],)": "NO result"
  },
  {
    "([45, 61, 17],)": [
      -0.3921119970626124,
      -0.9634435584929432
    ]
  },
  {
    "([85, 42, 63],)": "NO result"
  },
  {
    "([38, 50, 84],)": "NO result"
  },
  {
    "([66, 47, 79],)": "NO result"
  },
  {
    "([7, 22, 29],)": "NO result"
  },
  {
    "([10, 97, 47],)": [
      -0.5115094790929874,
      -9.188490520907013
    ]
  },
  {
    "([14, 61, 31],)": [
      -0.587380756432467,
      -3.7697621007103903
    ]
  },
  {
    "([87, 100, 82],)": "NO result"
  },
  {
    "([45, 85, 97],)": "NO result"
  },
  {
    "([77, 83, 21],)": [
      -0.4057254251384208,
      -0.6721966527836571
    ]
  },
  {
    "([95, 17, 61],)": "NO result"
  },
  {
    "([32, 30, 67],)": "NO result"
  },
  {
    "([93, 33, 7],)": "NO result"
  },
  {
    "([96, 59, 53],)": "NO result"
  },
  {
    "([32, 33, 54],)": "NO result"
  },
  {
    "([34, 54, 60],)": "NO result"
  },
  {
    "([46, 14, 92],)": "NO result"
  },
  {
    "([99, 44, 26],)": "NO result"
  },
  {
    "([32, 53, 90],)": "NO result"
  },
  {
    "([79, 92, 95],)": "NO result"
  },
  {
    "([82, 56, 34],)": "NO result"
  },
  {
    "([90, 58, 93],)": "NO result"
  },
  {
    "([75, 79, 91],)": "NO result"
  },
  {
    "([21, 98, 63],)": [
      -0.7698614133921902,
      -3.8968052532744766
    ]
  },
  {
    "([35, 1, 41],)": "NO result"
  },
  {
    "([76, 72, 69],)": "NO result"
  },
  {
    "([6, 50, 13],)": [
      -0.26866147882449987,
      -8.064671854508832
    ]
  },
  {
    "([78, 40, 65],)": "NO result"
  },
  {
    "([47, 8, 60],)": "NO result"
  },
  {
    "([62, 19, 69],)": "NO result"
  },
  {
    "([62, 52, 50],)": "NO result"
  },
  {
    "([55, 51, 27],)": "NO result"
  },
  {
    "([55, 100, 53],)": "NO result"
  },
  {
    "([16, 45, 55],)": "NO result"
  },
  {
    "([22, 11, 14],)": "NO result"
  },
  {
    "([92, 41, 43],)": "NO result"
  },
  {
    "([50, 50, 43],)": "NO result"
  },
  {
    "([23, 36, 80],)": "NO result"
  },
  {
    "([5, 1, 38],)": "NO result"
  },
  {
    "([97, 29, 45],)": "NO result"
  },
  {
    "([20, 32, 64],)": "NO result"
  },
  {
    "([67, 67, 46],)": "NO result"
  },
  {
    "([25, 87, 56],)": [
      -0.8525316907066484,
      -2.6274683092933513
    ]
  },
  {
    "([19, 59, 91],)": "NO result"
  },
  {
    "([41, 65, 84],)": "NO result"
  },
  {
    "([30, 21, 77],)": "NO result"
  },
  {
    "([14, 64, 33],)": [
      -0.5923900584100432,
      -3.9790385130185277
    ]
  },
  {
    "([74, 85, 54],)": "NO result"
  },
  {
    "([80, 98, 91],)": "NO result"
  },
  {
    "([50, 90, 56],)": "NO result"
  },
  {
    "([42, 4, 51],)": "NO result"
  },
  {
    "([17, 11, 62],)": "NO result"
  },
  {
    "([52, 80, 37],)": "NO result"
  },
  {
    "([10, 86, 97],)": [
      -1.3352065839252814,
      -7.264793416074719
    ]
  },
  {
    "([97, 94, 5],)": [
      -0.05648372181388259,
      -0.912588443134571
    ]
  },
  {
    "([1, 38, 86],)": [
      -2.416876048222999,
      -35.583123951777
    ]
  },
  {
    "([67, 7, 64],)": "NO result"
  },
  {
    "([1, 79, 18],)": [
      -0.22850906828211492,
      -78.77149093171789
    ]
  },
  {
    "([76, 66, 65],)": "NO result"
  },
  {
    "([16, 13, 69],)": "NO result"
  },
  {
    "([7, 14, 9],)": "NO result"
  },
  {
    "([46, 57, 66],)": "NO result"
  },
  {
    "([63, 93, 76],)": "NO result"
  },
  {
    "([46, 44, 60],)": "NO result"
  },
  {
    "([77, 27, 85],)": "NO result"
  },
  {
    "([77, 32, 81],)": "NO result"
  },
  {
    "([83, 6, 36],)": "NO result"
  },
  {
    "([4, 35, 29],)": [
      -0.9267214439665694,
      -7.823278556033431
    ]
  },
  {
    "([21, 55, 54],)": "NO result"
  },
  {
    "([58, 35, 7],)": "NO result"
  },
  {
    "([73, 12, 86],)": "NO result"
  },
  {
    "([52, 93, 86],)": "NO result"
  },
  {
    "([95, 73, 64],)": "NO result"
  },
  {
    "([48, 3, 87],)": "NO result"
  },
  {
    "([67, 23, 54],)": "NO result"
  },
  {
    "([74, 48, 1],)": [
      -0.021549236453944878,
      -0.6270994121947038
    ]
  },
  {
    "([73, 59, 5],)": [
      -0.09619497543850654,
      -0.7120242026436853
    ]
  },
  {
    "([27, 29, 80],)": "NO result"
  },
  {
    "([34, 97, 1],)": [
      -0.010346803252334483,
      -2.8425943732182537
    ]
  },
  {
    "([80, 70, 33],)": "NO result"
  },
  {
    "([63, 33, 12],)": "NO result"
  },
  {
    "([88, 92, 60],)": "NO result"
  },
  {
    "([49, 15, 16],)": "NO result"
  },
  {
    "([18, 88, 11],)": [
      -0.12837071270268532,
      -4.760518176186204
    ]
  },
  {
    "([76, 6, 78],)": "NO result"
  },
  {
    "([66, 76, 100],)": "NO result"
  },
  {
    "([92, 95, 55],)": "NO result"
  },
  {
    "([22, 61, 18],)": [
      -0.33573415169761633,
      -2.4369931210296567
    ]
  },
  {
    "([94, 52, 15],)": "NO result"
  },
  {
    "([79, 56, 32],)": "NO result"
  },
  {
    "([36, 52, 10],)": [
      -0.2284336434824673,
      -1.2160108009619772
    ]
  },
  {
    "([100, 49, 30],)": "NO result"
  },
  {
    "([10, 55, 87],)": "NO result"
  },
  {
    "([55, 9, 100],)": "NO result"
  },
  {
    "([9, 15, 24],)": "NO result"
  },
  {
    "([100, 19, 94],)": "NO result"
  },
  {
    "([2, 75, 52],)": [
      -0.7066494242338699,
      -36.79335057576613
    ]
  },
  {
    "([15, 5, 29],)": "NO result"
  },
  {
    "([26, 86, 65],)": [
      -1.1688646071954427,
      -2.138827700496865
    ]
  },
  {
    "([98, 65, 64],)": "NO result"
  },
  {
    "([61, 100, 50],)": "NO result"
  },
  {
    "([12, 96, 12],)": [
      -0.12701665379258328,
      -7.872983346207417
    ]
  },
  {
    "([35, 13, 69],)": "NO result"
  },
  {
    "([12, 31, 39],)": "NO result"
  },
  {
    "([90, 27, 65],)": "NO result"
  },
  {
    "([26, 8, 75],)": "NO result"
  },
  {
    "([59, 11, 86],)": "NO result"
  },
  {
    "([86, 47, 36],)": "NO result"
  },
  {
    "([84, 12, 80],)": "NO result"
  },
  {
    "([30, 57, 5],)": [
      -0.09219271783614857,
      -1.8078072821638513
    ]
  },
  {
    "([86, 44, 93],)": "NO result"
  },
  {
    "([87, 64, 73],)": "NO result"
  },
  {
    "([93, 79, 96],)": "NO result"
  },
  {
    "([89, 87, 21],)": [
      -0.43458623167981486,
      -0.5429418582078256
    ]
  },
  {
    "([35, 12, 69],)": "NO result"
  },
  {
    "([28, 14, 79],)": "NO result"
  },
  {
    "([81, 96, 31],)": "NO result"
  },
  {
    "([83, 80, 17],)": [
      -0.3162924447606323,
      -0.6475629769261148
    ]
  },
  {
    "([71, 15, 45],)": "NO result"
  },
  {
    "([30, 30, 94],)": "NO result"
  },
  {
    "([38, 86, 2],)": [
      -0.02349982781961582,
      -2.2396580669172264
    ]
  },
  {
    "([77, 36, 52],)": "NO result"
  },
  {
    "([94, 18, 3],)": "NO result"
  },
  {
    "([19, 67, 6],)": [
      -0.09194986217816548,
      -3.4343659272955187
    ]
  },
  {
    "([37, 77, 72],)": "NO result"
  },
  {
    "([79, 24, 87],)": "NO result"
  },
  {
    "([25, 53, 8],)": [
      -0.1635626067594012,
      -1.9564373932405987
    ]
  },
  {
    "([23, 50, 35],)": "NO result"
  },
  {
    "([3, 57, 43],)": [
      -0.7869829182615126,
      -18.21301708173849
    ]
  },
  {
    "([25, 95, 64],)": [
      -0.8753049234040401,
      -2.92469507659596
    ]
  },
  {
    "([29, 56, 89],)": "NO result"
  },
  {
    "([33, 46, 62],)": "NO result"
  },
  {
    "([19, 59, 36],)": [
      -0.8343503124233589,
      -2.270912845471378
    ]
  },
  {
    "([12, 61, 60],)": [
      -1.3333333333333333,
      -3.75
    ]
  },
  {
    "([67, 66, 81],)": "NO result"
  },
  {
    "([32, 100, 26],)": [
      -0.28621388395861636,
      -2.8387861160413834
    ]
  },
  {
    "([26, 29, 67],)": "NO result"
  },
  {
    "([55, 98, 90],)": "NO result"
  },
  {
    "([46, 52, 66],)": "NO result"
  },
  {
    "([94, 76, 32],)": "NO result"
  },
  {
    "([13, 93, 54],)": [
      -0.6374447993406929,
      -6.5164013545054615
    ]
  },
  {
    "([1, 89, 39],)": [
      -0.44038129987958996,
      -88.55961870012041
    ]
  },
  {
    "([55, 33, 26],)": "NO result"
  },
  {
    "([13, 63, 82],)": "NO result"
  },
  {
    "([18, 36, 27],)": "NO result"
  },
  {
    "([59, 90, 16],)": [
      -0.20544806024496287,
      -1.3199756685685966
    ]
  },
  {
    "([16, 22, 95],)": "NO result"
  },
  {
    "([20, 41, 68],)": "NO result"
  },
  {
    "([55, 67, 75],)": "NO result"
  },
  {
    "([84, 14, 79],)": "NO result"
  },
  {
    "([22, 87, 89],)": "NO result"
  },
  {
    "([88, 8, 86],)": "NO result"
  },
  {
    "([75, 26, 61],)": "NO result"
  },
  {
    "([7, 59, 26],)": [
      -0.46649725075859855,
      -7.96207417781283
    ]
  },
  {
    "([85, 76, 5],)": [
      -0.07150847765853252,
      -0.8226091694002909
    ]
  },
  {
    "([34, 55, 4],)": [
      -0.07632885850516047,
      -1.541318200318369
    ]
  },
  {
    "([7, 4, 80],)": "NO result"
  },
  {
    "([19, 66, 84],)": "NO result"
  },
  {
    "([38, 26, 34],)": "NO result"
  },
  {
    "([64, 96, 71],)": "NO result"
  },
  {
    "([30, 21, 88],)": "NO result"
  },
  {
    "([92, 20, 53],)": "NO result"
  },
  {
    "([89, 3, 56],)": "NO result"
  },
  {
    "([11, 7, 36],)": "NO result"
  },
  {
    "([54, 25, 36],)": "NO result"
  },
  {
    "([96, 47, 78],)": "NO result"
  },
  {
    "([63, 60, 96],)": "NO result"
  },
  {
    "([55, 12, 56],)": "NO result"
  },
  {
    "([41, 88, 52],)": "NO result"
  },
  {
    "([86, 50, 61],)": "NO result"
  },
  {
    "([23, 37, 13],)": [
      -0.5184142078703065,
      -1.0902814443036066
    ]
  },
  {
    "([72, 73, 45],)": "NO result"
  },
  {
    "([24, 87, 74],)": [
      -1.363252944732337,
      -2.261747055267663
    ]
  },
  {
    "([39, 77, 47],)": "NO result"
  },
  {
    "([52, 63, 70],)": "NO result"
  },
  {
    "([61, 54, 33],)": "NO result"
  },
  {
    "([35, 49, 49],)": "NO result"
  },
  {
    "([53, 27, 25],)": "NO result"
  },
  {
    "([44, 71, 84],)": "NO result"
  },
  {
    "([28, 56, 54],)": "NO result"
  },
  {
    "([41, 28, 49],)": "NO result"
  },
  {
    "([42, 40, 55],)": "NO result"
  },
  {
    "([98, 8, 34],)": "NO result"
  },
  {
    "([38, 2, 87],)": "NO result"
  },
  {
    "([69, 11, 50],)": "NO result"
  },
  {
    "([23, 25, 89],)": "NO result"
  },
  {
    "([2, 35, 91],)": [
      -3.1766257975980112,
      -14.32337420240199
    ]
  },
  {
    "([92, 33, 85],)": "NO result"
  },
  {
    "([4, 74, 52],)": [
      -0.7316374812995896,
      -17.76836251870041
    ]
  },
  {
    "([28, 28, 55],)": "NO result"
  },
  {
    "([8, 55, 7],)": [
      -0.12972034440018954,
      -6.745279655599811
    ]
  },
  {
    "([91, 55, 51],)": "NO result"
  },
  {
    "([98, 63, 19],)": "NO result"
  },
  {
    "([100, 34, 52],)": "NO result"
  },
  {
    "([98, 82, 56],)": "NO result"
  },
  {
    "([67, 17, 12],)": "NO result"
  },
  {
    "([12, 90, 71],)": [
      -0.8959093684093821,
      -6.604090631590618
    ]
  },
  {
    "([12, 88, 2],)": [
      -0.02279814848742549,
      -7.310535184845908
    ]
  },
  {
    "([95, 87, 73],)": "NO result"
  },
  {
    "([41, 32, 91],)": "NO result"
  },
  {
    "([23, 20, 91],)": "NO result"
  },
  {
    "([83, 77, 99],)": "NO result"
  },
  {
    "([13, 28, 10],)": [
      -0.45199704579723377,
      -1.70184910804892
    ]
  },
  {
    "([47, 94, 53],)": "NO result"
  },
  {
    "([61, 81, 9],)": [
      -0.1223922406833138,
      -1.2054766117757028
    ]
  },
  {
    "([2, 93, 21],)": [
      -0.22691376031441024,
      -46.27308623968559
    ]
  },
  {
    "([55, 77, 62],)": "NO result"
  },
  {
    "([66, 52, 33],)": "NO result"
  },
  {
    "([54, 93, 92],)": "NO result"
  },
  {
    "([73, 18, 62],)": "NO result"
  },
  {
    "([59, 6, 18],)": "NO result"
  },
  {
    "([24, 98, 91],)": [
      -1.4278783390559902,
      -2.6554549942773433
    ]
  },
  {
    "([22, 90, 76],)": [
      -1.191441171452003,
      -2.899467919457088
    ]
  },
  {
    "([19, 67, 75],)": "NO result"
  },
  {
    "([87, 46, 19],)": "NO result"
  },
  {
    "([38, 40, 38],)": "NO result"
  },
  {
    "([52, 95, 66],)": "NO result"
  },
  {
    "([14, 88, 85],)": [
      -1.191928530893191,
      -5.093785754821094
    ]
  },
  {
    "([65, 75, 87],)": "NO result"
  },
  {
    "([37, 12, 46],)": "NO result"
  },
  {
    "([50, 43, 50],)": "NO result"
  },
  {
    "([43, 99, 87],)": "NO result"
  },
  {
    "([20, 45, 92],)": "NO result"
  },
  {
    "([86, 13, 18],)": "NO result"
  },
  {
    "([69, 23, 28],)": "NO result"
  },
  {
    "([58, 35, 27],)": "NO result"
  },
  {
    "([95, 74, 83],)": "NO result"
  },
  {
    "([89, 45, 80],)": "NO result"
  },
  {
    "([52, 29, 8],)": "NO result"
  },
  {
    "([77, 1, 73],)": "NO result"
  },
  {
    "([86, 3, 4],)": "NO result"
  },
  {
    "([70, 20, 83],)": "NO result"
  },
  {
    "([53, 7, 85],)": "NO result"
  },
  {
    "([91, 25, 37],)": "NO result"
  },
  {
    "([66, 94, 12],)": [
      -0.1417718113721603,
      -1.282470612870264
    ]
  },
  {
    "([91, 13, 4],)": "NO result"
  },
  {
    "([56, 84, 44],)": "NO result"
  },
  {
    "([23, 46, 97],)": "NO result"
  },
  {
    "([94, 51, 24],)": "NO result"
  },
  {
    "([36, 69, 48],)": "NO result"
  },
  {
    "([46, 30, 88],)": "NO result"
  }
]